bpmll/__init__.py
bpmll/bpmll.py
bpmll-1.0.0.dist-info/LICENSE
bpmll-1.0.0.dist-info/METADATA
bpmll-1.0.0.dist-info/WHEEL
bpmll-1.0.0.dist-info/top_level.txt
bpmll-1.0.0.dist-info/zip-safe
bpmll-1.0.0.dist-info/RECORD
