Metadata-Version: 2.1
Name: bpmll
Version: 1.0.0
Summary: BP-MLL loss function for tensorflow
Home-page: https://github.com/vanHavel/bp-mll-tensorflow
Author: Lukas Huwald
Author-email: dev.lukas.huwald@gmail.com
License: MIT
Keywords: bpmll
Platform: UNKNOWN
Classifier: License :: OSI Approved :: MIT License
Classifier: Operating System :: OS Independent
Classifier: Programming Language :: Python :: 3
Classifier: Topic :: Scientific/Engineering :: Artificial Intelligence
Requires-Python: >=3.5
Requires-Dist: tensorflow
